{
  "hash": "2720c0c865b5d44d524bf22993a1cb8e",
  "result": {
    "markdown": "---\ntitle: \"Week 4\"\nsubtitle: \"Feature Selection and LASSO\"\neditor: visual\n---\n\n\n::: callout-important\n**Homework 1 due Friday, Feb 9, 11:59 PM**\n:::\n\n## Participate\n\n🖥️ [Slides - Lasso](/slides/06-lasso-cv.html)\n\n`<svg aria-hidden=\"true\" role=\"img\" viewBox=\"0 0 512 512\" style=\"height:1em;width:1em;vertical-align:-0.125em;margin-left:auto;margin-right:auto;font-size:inherit;fill:currentColor;overflow:visible;position:relative;\"><path d=\"M64 256V160H224v96H64zm0 64H224v96H64V320zm224 96V320H448v96H288zM448 256H288V160H448v96zM64 32C28.7 32 0 60.7 0 96V416c0 35.3 28.7 64 64 64H448c35.3 0 64-28.7 64-64V96c0-35.3-28.7-64-64-64H64z\"/></svg>`{=html} [Data set - Prostate](https://hastie.su.domains/ElemStatLearn/)\n\n## Reading and Resources\n\n📖 [ISL Ch 6.1, 6.2](https://www.statlearning.com/)\n\n## Perform\n\n<!-- 📋 [Lab-08 Tibbles and Pipes](/exercise/lab08-tibble.html) -->\n\n<!-- 📋 [Lab-09 NumPy and pandas](/exercise/lab09-numpy.html) -->\n\n<br><br>\n\n::: {style=\"font-size: 0.875em;\"}\nBack to [course schedule](/ \"Course schedule\") ⏎\n:::\n",
    "supporting": [
      "week-4_files"
    ],
    "filters": [
      "rmarkdown/pagebreak.lua"
    ],
    "includes": {},
    "engineDependencies": {},
    "preserve": {},
    "postProcess": true
  }
}